MacKaifaPeizhiShouce/README.md
MacKaifaPeizhiShouce/__init__.py
MacKaifaPeizhiShouce/__main__.py
MacKaifaPeizhiShouce/file.epub
MacKaifaPeizhiShouce/index.html
MacKaifaPeizhiShouce/css/__init__.py
MacKaifaPeizhiShouce/css/annotations.css
MacKaifaPeizhiShouce/css/main.css
MacKaifaPeizhiShouce/css/normalize.css
MacKaifaPeizhiShouce/css/popup.css
MacKaifaPeizhiShouce/font/__init__.py
MacKaifaPeizhiShouce/font/fontello.eot
MacKaifaPeizhiShouce/font/fontello.svg
MacKaifaPeizhiShouce/font/fontello.ttf
MacKaifaPeizhiShouce/font/fontello.woff
MacKaifaPeizhiShouce/img/__init__.py
MacKaifaPeizhiShouce/img/annotator-glyph-sprite.png
MacKaifaPeizhiShouce/img/annotator-icon-sprite.png
MacKaifaPeizhiShouce/img/apple-touch-icon.png
MacKaifaPeizhiShouce/img/cancelfullscreen.png
MacKaifaPeizhiShouce/img/close.png
MacKaifaPeizhiShouce/img/fullscreen.png
MacKaifaPeizhiShouce/img/loader.gif
MacKaifaPeizhiShouce/img/menu-icon.png
MacKaifaPeizhiShouce/img/save.png
MacKaifaPeizhiShouce/img/saved.png
MacKaifaPeizhiShouce/img/settings-s.png
MacKaifaPeizhiShouce/img/settings.png
MacKaifaPeizhiShouce/img/star.png
MacKaifaPeizhiShouce/js/__init__.py
MacKaifaPeizhiShouce/js/epub.js
MacKaifaPeizhiShouce/js/epub.min.js
MacKaifaPeizhiShouce/js/epub.min.map
MacKaifaPeizhiShouce/js/hooks.min.js
MacKaifaPeizhiShouce/js/hooks.min.map
MacKaifaPeizhiShouce/js/reader.js
MacKaifaPeizhiShouce/js/reader.js.map
MacKaifaPeizhiShouce/js/reader.min.js
MacKaifaPeizhiShouce/js/reader.min.map
MacKaifaPeizhiShouce/js/hooks/__init__.py
MacKaifaPeizhiShouce/js/hooks/extensions/__init__.py
MacKaifaPeizhiShouce/js/hooks/extensions/highlight.js
MacKaifaPeizhiShouce/js/libs/__init__.py
MacKaifaPeizhiShouce/js/libs/jquery.min.js
MacKaifaPeizhiShouce/js/libs/localforage.min.js
MacKaifaPeizhiShouce/js/libs/screenfull.js
MacKaifaPeizhiShouce/js/libs/screenfull.min.js
MacKaifaPeizhiShouce/js/libs/zip.min.js
MacKaifaPeizhiShouce/js/plugins/__init__.py
MacKaifaPeizhiShouce/js/plugins/hypothesis.js
mac_kaifa_peizhi_shouce-2024.2.29.0.dist-info/METADATA
mac_kaifa_peizhi_shouce-2024.2.29.0.dist-info/WHEEL
mac_kaifa_peizhi_shouce-2024.2.29.0.dist-info/entry_points.txt
mac_kaifa_peizhi_shouce-2024.2.29.0.dist-info/top_level.txt
mac_kaifa_peizhi_shouce-2024.2.29.0.dist-info/RECORD
